nc_mcp-0.1.2.dist-info/licenses/LICENSE
nc_mcp_server/__init__.py
nc_mcp_server/main.py
nc_mcp-0.1.2.dist-info/METADATA
nc_mcp-0.1.2.dist-info/WHEEL
nc_mcp-0.1.2.dist-info/top_level.txt
nc_mcp-0.1.2.dist-info/RECORD
